odoo/addons/partner_email_duplicate_warn/README.rst
odoo/addons/partner_email_duplicate_warn/__init__.py
odoo/addons/partner_email_duplicate_warn/__manifest__.py
odoo/addons/partner_email_duplicate_warn/i18n/fr.po
odoo/addons/partner_email_duplicate_warn/i18n/hr.po
odoo/addons/partner_email_duplicate_warn/i18n/it.po
odoo/addons/partner_email_duplicate_warn/i18n/partner_email_duplicate_warn.pot
odoo/addons/partner_email_duplicate_warn/models/__init__.py
odoo/addons/partner_email_duplicate_warn/models/res_partner.py
odoo/addons/partner_email_duplicate_warn/readme/CONFIGURE.md
odoo/addons/partner_email_duplicate_warn/readme/CONTRIBUTORS.md
odoo/addons/partner_email_duplicate_warn/readme/DESCRIPTION.md
odoo/addons/partner_email_duplicate_warn/readme/ROADMAP.md
odoo/addons/partner_email_duplicate_warn/readme/USAGE.md
odoo/addons/partner_email_duplicate_warn/static/description/icon.png
odoo/addons/partner_email_duplicate_warn/static/description/index.html
odoo/addons/partner_email_duplicate_warn/static/description/partner_warn_banner.png
odoo/addons/partner_email_duplicate_warn/tests/__init__.py
odoo/addons/partner_email_duplicate_warn/tests/test_email_duplicate.py
odoo/addons/partner_email_duplicate_warn/views/res_partner.xml
odoo_addon_partner_email_duplicate_warn-18.0.1.0.0.3.dist-info/METADATA
odoo_addon_partner_email_duplicate_warn-18.0.1.0.0.3.dist-info/WHEEL
odoo_addon_partner_email_duplicate_warn-18.0.1.0.0.3.dist-info/top_level.txt
odoo_addon_partner_email_duplicate_warn-18.0.1.0.0.3.dist-info/RECORD
